pytbangla/__init__.py
pytbangla/ui.py
pytbangla-1.0.5.dist-info/licenses/LICENSE
pytbangla-1.0.5.dist-info/METADATA
pytbangla-1.0.5.dist-info/WHEEL
pytbangla-1.0.5.dist-info/top_level.txt
pytbangla-1.0.5.dist-info/RECORD
