Metadata-Version: 2.4
Name: PytBangla
Version: 1.0.5
Summary: Simple python library to write programs in bangla language
Author: Mohammad Mahfuz Rahman
Author-email: mahfuzrahman0712@gmail.com
Keywords: speech recognition,text to speech,take command,command taker,python in bangla,programming,Python Organization,Django,Flask,tkinter,python,web development,app development,django developer,python bangladesh community,what is Python,What is coding,What is programming,PytBangla
Classifier: Development Status :: 1 - Planning
Classifier: Intended Audience :: Developers
Classifier: License :: OSI Approved :: MIT License
Classifier: Programming Language :: Python :: 3
Classifier: Operating System :: Microsoft :: Windows
License-File: LICENSE
Requires-Dist: speechrecognition
Requires-Dist: pyttsx3
Requires-Dist: pyaudio
Requires-Dist: pyautogui
Requires-Dist: pywhatkit
Requires-Dist: wikipedia
Requires-Dist: pyjokes
Requires-Dist: secure-smtplib
Requires-Dist: customtkinter
Requires-Dist: pandas
Requires-Dist: requests
Requires-Dist: beautifulsoup4
Requires-Dist: opencv-python
Requires-Dist: numpy
Requires-Dist: pillow
Dynamic: author
Dynamic: author-email
Dynamic: classifier
Dynamic: description
Dynamic: description-content-type
Dynamic: keywords
Dynamic: license-file
Dynamic: requires-dist
Dynamic: summary
